README
n3d.py
setup.py
n3d.egg-info/PKG-INFO
n3d.egg-info/SOURCES.txt
n3d.egg-info/dependency_links.txt
n3d.egg-info/entry_points.txt
n3d.egg-info/requires.txt
n3d.egg-info/top_level.txt