Metadata-Version: 1.1
Name: n3d
Version: 0.3.2
Summary: Utility for step-by-step application deployment
Home-page: http://github.com/grudko/n3d
Author: Anton Grudko
Author-email: grudko@gmail.com
License: UNKNOWN
Platform: UNKNOWN
Classifier: Development Status :: 4 - Beta
Classifier: Environment :: Console
Classifier: Intended Audience :: Developers
Classifier: Intended Audience :: System Administrators
Classifier: License :: OSI Approved :: GNU Lesser General Public License v3 (LGPLv3)
Classifier: Operating System :: POSIX
Classifier: Programming Language :: Python
Classifier: Topic :: Software Development :: Build Tools
